apgorm/__init__.py
apgorm/__main__.py
apgorm/connection.py
apgorm/constraints/__init__.py
apgorm/constraints/check.py
apgorm/constraints/constraint.py
apgorm/constraints/exclude.py
apgorm/constraints/foreign_key.py
apgorm/constraints/primary_key.py
apgorm/constraints/unique.py
apgorm/converter.py
apgorm/database.py
apgorm/exceptions.py
apgorm/field.py
apgorm/indexes.py
apgorm/manytomany.py
apgorm/migrations/__init__.py
apgorm/migrations/applied_migration.py
apgorm/migrations/apply_migration.py
apgorm/migrations/create_migration.py
apgorm/migrations/describe.py
apgorm/migrations/migration.py
apgorm/model.py
apgorm/py.typed
apgorm/sql/__init__.py
apgorm/sql/generators/__init__.py
apgorm/sql/generators/alter.py
apgorm/sql/generators/query.py
apgorm/sql/query_builder.py
apgorm/sql/sql.py
apgorm/types/__init__.py
apgorm/types/array.py
apgorm/types/base_type.py
apgorm/types/binary.py
apgorm/types/bitstr.py
apgorm/types/boolean.py
apgorm/types/character.py
apgorm/types/date.py
apgorm/types/geometric.py
apgorm/types/json_type.py
apgorm/types/monetary.py
apgorm/types/network.py
apgorm/types/numeric.py
apgorm/types/uuid_type.py
apgorm/types/xml_type.py
apgorm/undefined.py
apgorm/utils/__init__.py
apgorm/utils/lazy_list.py
apgorm-1.0.0b13.dist-info/LICENSE
apgorm-1.0.0b13.dist-info/WHEEL
apgorm-1.0.0b13.dist-info/METADATA
apgorm-1.0.0b13.dist-info/RECORD
