Metadata-Version: 2.1
Name: apgorm
Version: 1.0.0b13
Summary: A fully type-checked asynchronous ORM wrapped around asyncpg.
Home-page: https://github.com/TrigonDev/apgorm
License: MIT
Keywords: postgres,postgresql,asyncpg,asyncio,orm
Author: Circuit
Requires-Python: >=3.8,<4.0
Classifier: License :: OSI Approved :: MIT License
Classifier: Programming Language :: Python :: 3
Classifier: Programming Language :: Python :: 3.8
Classifier: Programming Language :: Python :: 3.9
Classifier: Programming Language :: Python :: 3.10
Requires-Dist: asyncpg (>=0.25,<0.27)
Requires-Dist: pydantic (>=1.9.0,<2.0.0)
Project-URL: Documentation, https://github.com/TrigonDev/apgorm/wiki
Project-URL: Repository, https://github.com/TrigonDev/apgorm
